sus/__init__.py
sus/__main__.py
sus/client/__init__.py
sus/client/client.py
sus/client/protocol.py
sus/common/__init__.py
sus/common/exceptions.py
sus/common/globals.py
sus/common/util.py
sus/server/__init__.py
sus/server/handler.py
sus/server/protocol.py
sus/server/server.py
suspycious-0.1.2a0.dist-info/LICENSE
suspycious-0.1.2a0.dist-info/METADATA
suspycious-0.1.2a0.dist-info/WHEEL
suspycious-0.1.2a0.dist-info/entry_points.txt
suspycious-0.1.2a0.dist-info/RECORD
